CHANGELOG.md
testbrain/contrib/__init__.py
testbrain/contrib/client/__init__.py
testbrain/contrib/client/adapters.py
testbrain/contrib/client/auth.py
testbrain/contrib/client/client.py
testbrain/contrib/client/compat.py
testbrain/contrib/client/exceptions.py
testbrain/contrib/client/utils.py
testbrain/contrib/report/__init__.py
testbrain/contrib/report/converters/__init__.py
testbrain/contrib/report/converters/allure.py
testbrain/contrib/report/converters/base.py
testbrain/contrib/report/converters/junit.py
testbrain/contrib/report/converters/mstest.py
testbrain/contrib/report/converters/testbrain.py
testbrain/contrib/report/mergers/__init__.py
testbrain/contrib/report/mergers/base.py
testbrain/contrib/report/mergers/junit.py
testbrain/contrib/report/mergers/testbrain.py
testbrain/contrib/report/models/__init__.py
testbrain/contrib/report/models/allure.py
testbrain/contrib/report/models/junit.py
testbrain/contrib/report/models/mstest.py
testbrain/contrib/report/models/testbrain.py
testbrain/contrib/report/models/xunit2.py
testbrain/contrib/report/parsers/__init__.py
testbrain/contrib/report/parsers/allure.py
testbrain/contrib/report/parsers/base.py
testbrain/contrib/report/parsers/junit.py
testbrain/contrib/report/parsers/mstest.py
testbrain/contrib/report/parsers/testbrain.py
testbrain/contrib/report/utils.py
testbrain/contrib/scm/__init__.py
testbrain/contrib/scm/base.py
testbrain/contrib/scm/exceptions.py
testbrain/contrib/scm/git/__init__.py
testbrain/contrib/scm/git/patterns.py
testbrain/contrib/scm/git/process.py
testbrain/contrib/scm/git/utils.py
testbrain/contrib/scm/mercurial/__init__.py
testbrain/contrib/scm/svn/__init__.py
testbrain/contrib/scm/tfvc/__init__.py
testbrain/contrib/scm/tfvc/appsurifytfs.py
testbrain/contrib/scm/tfvc/patterns.py
testbrain/contrib/scm/tfvc/process.py
testbrain/contrib/scm/tfvc/utils.py
testbrain/contrib/system/__init__.py
testbrain/contrib/system/crashdump.py
testbrain/contrib/system/platform.py
appsurify_testbrain_contrib-2024.1.25.dist-info/METADATA
appsurify_testbrain_contrib-2024.1.25.dist-info/WHEEL
appsurify_testbrain_contrib-2024.1.25.dist-info/RECORD
